topsis/__init__.py
topsis/topsis.py
topsis_pariza_102303391-0.0.1.dist-info/METADATA
topsis_pariza_102303391-0.0.1.dist-info/WHEEL
topsis_pariza_102303391-0.0.1.dist-info/entry_points.txt
topsis_pariza_102303391-0.0.1.dist-info/top_level.txt
topsis_pariza_102303391-0.0.1.dist-info/RECORD
