Metadata-Version: 2.4
Name: Topsis-Pariza-102303391
Version: 0.0.1
Summary: TOPSIS implementation as a command-line Python package
Author: Pariza Singh Kandol
Requires-Dist: pandas
Requires-Dist: numpy
Dynamic: author
Dynamic: requires-dist
Dynamic: summary
